<?xml version="1.0" ?>
<annotation>
    <filename>05594.jpg</filename>
    <size>
        <width>256</width>
        <height>256</height>
        <depth>3</depth>
    </size>
    <object>
        <name>boat</name>
        <bndbox>
            <xmin>74</xmin>
            <ymin>86</ymin>
            <xmax>119</xmax>
            <ymax>124</ymax>
        </bndbox>
    </object>
    <object>
        <name>boat</name>
        <bndbox>
            <xmin>217</xmin>
            <ymin>161</ymin>
            <xmax>237</xmax>
            <ymax>184</ymax>
        </bndbox>
    </object>
    <object>
        <name>boat</name>
        <bndbox>
            <xmin>76</xmin>
            <ymin>224</ymin>
            <xmax>107</xmax>
            <ymax>249</ymax>
        </bndbox>
    </object>
</annotation>
