<?xml version="1.0" ?>
<annotation>
    <filename>06011.jpg</filename>
    <size>
        <width>256</width>
        <height>256</height>
        <depth>3</depth>
    </size>
    <object>
        <name>boat</name>
        <bndbox>
            <xmin>114</xmin>
            <ymin>24</ymin>
            <xmax>141</xmax>
            <ymax>81</ymax>
        </bndbox>
    </object>
    <object>
        <name>boat</name>
        <bndbox>
            <xmin>137</xmin>
            <ymin>103</ymin>
            <xmax>161</xmax>
            <ymax>164</ymax>
        </bndbox>
    </object>
    <object>
        <name>boat</name>
        <bndbox>
            <xmin>151</xmin>
            <ymin>183</ymin>
            <xmax>173</xmax>
            <ymax>236</ymax>
        </bndbox>
    </object>
    <object>
        <name>boat</name>
        <bndbox>
            <xmin>48</xmin>
            <ymin>214</ymin>
            <xmax>78</xmax>
            <ymax>233</ymax>
        </bndbox>
    </object>
    <object>
        <name>boat</name>
        <bndbox>
            <xmin>81</xmin>
            <ymin>233</ymin>
            <xmax>112</xmax>
            <ymax>252</ymax>
        </bndbox>
    </object>
</annotation>
