<?xml version="1.0" ?>
<annotation>
    <filename>16632.jpg</filename>
    <size>
        <width>256</width>
        <height>256</height>
        <depth>3</depth>
    </size>
    <object>
        <name>boat</name>
        <bndbox>
            <xmin>8</xmin>
            <ymin>163</ymin>
            <xmax>35</xmax>
            <ymax>196</ymax>
        </bndbox>
    </object>
    <object>
        <name>boat</name>
        <bndbox>
            <xmin>95</xmin>
            <ymin>69</ymin>
            <xmax>119</xmax>
            <ymax>95</ymax>
        </bndbox>
    </object>
    <object>
        <name>boat</name>
        <bndbox>
            <xmin>145</xmin>
            <ymin>0</ymin>
            <xmax>170</xmax>
            <ymax>19</ymax>
        </bndbox>
    </object>
    <object>
        <name>boat</name>
        <bndbox>
            <xmin>143</xmin>
            <ymin>218</ymin>
            <xmax>167</xmax>
            <ymax>241</ymax>
        </bndbox>
    </object>
</annotation>
