<?xml version="1.0" ?>
<annotation>
    <filename>26706.jpg</filename>
    <size>
        <width>256</width>
        <height>256</height>
        <depth>3</depth>
    </size>
    <object>
        <name>boat</name>
        <bndbox>
            <xmin>82</xmin>
            <ymin>94</ymin>
            <xmax>94</xmax>
            <ymax>136</ymax>
        </bndbox>
    </object>
    <object>
        <name>boat</name>
        <bndbox>
            <xmin>49</xmin>
            <ymin>228</ymin>
            <xmax>76</xmax>
            <ymax>255</ymax>
        </bndbox>
    </object>
</annotation>
